nginxauthdaemon/__init__.py
nginxauthdaemon/auth.py
nginxauthdaemon/config.py
nginxauthdaemon/crowdauth.py
nginxauthdaemon/nginxauthdaemon.py
nginxauthdaemon/static/login-sprite.png
nginxauthdaemon/templates/login.html
nginxauthdaemon-1.1.0.dist-info/DESCRIPTION.rst
nginxauthdaemon-1.1.0.dist-info/METADATA
nginxauthdaemon-1.1.0.dist-info/RECORD
nginxauthdaemon-1.1.0.dist-info/WHEEL
nginxauthdaemon-1.1.0.dist-info/metadata.json
nginxauthdaemon-1.1.0.dist-info/top_level.txt
