Metadata-Version: 2.0
Name: nginxauthdaemon
Version: 1.1.0
Summary: Authentication daemon for nginx-proxied or nginx-served applications
Home-page: https://github.com/akurdyukov/nginxauthdaemon
Author: Alik Kurdyukov
Author-email: akurdyukov@gmail.com
License: MIT
Keywords: nginx auth
Platform: UNKNOWN
Classifier: Development Status :: 3 - Alpha
Classifier: Intended Audience :: Developers
Classifier: Intended Audience :: System Administrators
Classifier: Topic :: Internet :: WWW/HTTP
Classifier: License :: OSI Approved :: MIT License
Classifier: Programming Language :: Python :: 2
Classifier: Programming Language :: Python :: 2.6
Classifier: Programming Language :: Python :: 2.7
Classifier: Programming Language :: Python :: 3
Classifier: Programming Language :: Python :: 3.3
Classifier: Programming Language :: Python :: 3.4
Classifier: Programming Language :: Python :: 3.5
Requires-Dist: Crowd (==1.0.0)
Requires-Dist: Flask (==0.11.1)
Requires-Dist: Jinja2 (==2.8)
Requires-Dist: MarkupSafe (==0.23)
Requires-Dist: Werkzeug (==0.11.10)
Requires-Dist: click (==6.6)
Requires-Dist: itsdangerous (==0.24)
Requires-Dist: lxml (==3.6.1)
Requires-Dist: pyasn1 (==0.1.9)
Requires-Dist: pycrypto (==2.6.1)
Requires-Dist: requests (==2.11.0)
Provides-Extra: dev
Requires-Dist: check-manifest; extra == 'dev'
Provides-Extra: test
Requires-Dist: coverage; extra == 'test'
